tap_getcensus/__init__.py
tap_getcensus/__main__.py
tap_getcensus/client.py
tap_getcensus/streams.py
tap_getcensus/tap.py
tap_getcensus-0.0.2.dist-info/METADATA
tap_getcensus-0.0.2.dist-info/WHEEL
tap_getcensus-0.0.2.dist-info/entry_points.txt
tap_getcensus-0.0.2.dist-info/RECORD
