Metadata-Version: 2.1
Name: tap-getcensus
Version: 0.0.2
Summary: Singer tap for the Census Operational Analytics Platform, built with the Meltano SDK for Singer Taps.
Home-page: https://github.com/edgarrmondragon/tap-getcensus
License: Apache-2.0
Keywords: ELT,singer.io,Census
Author: Edgar Ramírez-Mondragón
Author-email: edgarrm358@gmail.com
Maintainer: Edgar Ramírez-Mondragón
Maintainer-email: edgarrm358@gmail.com
Requires-Python: >=3.7.1,<3.12
Classifier: License :: OSI Approved :: Apache Software License
Classifier: Programming Language :: Python :: 3
Classifier: Programming Language :: Python :: 3.8
Classifier: Programming Language :: Python :: 3.9
Classifier: Programming Language :: Python :: 3.10
Classifier: Programming Language :: Python :: 3.11
Requires-Dist: singer-sdk (==0.23.0)
Project-URL: Documentation, https://github.com/edgarrmondragon/tap-getcensus/#readme
Project-URL: Repository, https://github.com/edgarrmondragon/tap-getcensus
